{
  "category": "Epic",
  "description": "# CompletionDetector Durability\n\nPersist epic/milestone/project completion dedup state to disk so server restarts do not re-fire completion events and ceremonies.\n\n## Phases\n1. Persist and reload CompletionDetector dedup state",
  "title": "[Epic] CompletionDetector Durability",
  "status": "done",
  "isEpic": true,
  "epicColor": "#4F46E5",
  "branchName": "epic/completiondetector-durability",
  "projectSlug": "e2e-pipeline-hardening",
  "id": "feature-1772856637958-j1b2je1mg",
  "descriptionHistory": [
    {
      "description": "# CompletionDetector Durability\n\nPersist epic/milestone/project completion dedup state to disk so server restarts do not re-fire completion events and ceremonies.\n\n## Phases\n1. Persist and reload CompletionDetector dedup state",
      "timestamp": "2026-03-07T04:10:37.958Z",
      "source": "initial"
    }
  ],
  "createdAt": "2026-03-07T04:10:37.958Z",
  "statusHistory": [
    {
      "from": null,
      "to": "backlog",
      "timestamp": "2026-03-07T04:10:37.958Z",
      "reason": "Feature created"
    },
    {
      "from": "backlog",
      "to": "done",
      "timestamp": "2026-03-07T04:44:53.379Z"
    }
  ],
  "featureType": "code",
  "completedAt": "2026-03-07T04:44:53.379Z"
}